neatplan/__init__.py
neatplan/__main__.py
neatplan/neatplan.py
neatplan-0.3.0.dist-info/METADATA
neatplan-0.3.0.dist-info/WHEEL
neatplan-0.3.0.dist-info/entry_points.txt
neatplan-0.3.0.dist-info/licenses/LICENSE
neatplan-0.3.0.dist-info/RECORD
