Metadata-Version: 2.1
Name: neatplan
Version: 0.3.0
Summary: nginx-style network configuration
Project-URL: Homepage, https://github.com/c0m4r/neatplan
Project-URL: Issues, https://github.com/c0m4r/neatplan/issues
Project-URL: Changelog, https://github.com/c0m4r/neatplan/blob/main/CHANGELOG
Author-email: c0m4r <github@wolfet.pl>
License: GPLv3
License-File: LICENSE
Classifier: Environment :: Console
Classifier: Intended Audience :: System Administrators
Classifier: License :: OSI Approved :: GNU General Public License v3 (GPLv3)
Classifier: Operating System :: POSIX :: Linux
Classifier: Programming Language :: Python :: 3
Classifier: Topic :: System :: Networking
Classifier: Topic :: System :: Operating System
Requires-Python: >=3.6
Requires-Dist: crossplane>=0.5.8
